pandas_xyz/__init__.py
pandas_xyz/_decorators.py
pandas_xyz/accessor.py
pandas_xyz/algorithms.py
pandas_xyz/algorithms_old.py
pandas_xyz/scalar.py
pandas_xyz-0.0.5.dist-info/LICENSE
pandas_xyz-0.0.5.dist-info/METADATA
pandas_xyz-0.0.5.dist-info/WHEEL
pandas_xyz-0.0.5.dist-info/top_level.txt
pandas_xyz-0.0.5.dist-info/RECORD
