Metadata-Version: 2.1
Name: pandas-xyz
Version: 0.0.5
Summary: Geospatial calculation accessor for pandas DataFrames.
Home-page: https://github.com/aaron-schroeder/pandas-xyz
Author: Aaron Schroeder
Author-email: aaron@trailzealot.com
License: MIT
Project-URL: Documentation, https://pandas-xyz.readthedocs.io/en/v0.0.5/
Platform: UNKNOWN
Classifier: License :: OSI Approved :: MIT License
Classifier: Intended Audience :: Developers
Classifier: Programming Language :: Python :: 3
Classifier: Programming Language :: Python :: 3.7
Requires-Dist: numpy (>=1.19.5)
Requires-Dist: pandas (>=1.2.0)
Requires-Dist: scipy
